{
  "topLabel": "FRONTEND FRAMEWORKS",
  "mainTitle": {
    "left": "SolidJS",
    "right": "Qwik",
    "vs": "vs"
  },
  "leftSub": "Reactive UI Library",
  "rightSub": "Resumable Frontend",
  "leftColor": "#1e3a8a",
  "rightColor": "#9333ea",
  "badge": "THE 7 CORE DIFFERENCES",
  "differences": [
    {
      "title": "1. REACTIVITY MODEL",
      "leftTitle": "Fine-grained reactivity",
      "rightTitle": "Resumability at core",
      "leftDesc": "SolidJS uses signals for direct DOM updates, offering performance benefits.",
      "rightDesc": "Qwik optimizes initial load by pausing execution and resuming on user interaction.",
      "leftIcon": "Activity",
      "rightIcon": "Server",
      "leftVisualText": "Signals",
      "rightVisualText": "Resumability"
    },
    {
      "title": "2. INITIAL LOAD",
      "leftTitle": "Fast, no hydration",
      "rightTitle": "Instant, no hydration",
      "leftDesc": "SolidJS has zero hydration overhead, directly rendering components.",
      "rightDesc": "Qwik aims for near-zero hydration with its resumability approach.",
      "leftIcon": "Zap",
      "rightIcon": "Zap",
      "leftVisualText": "Zero Hydration",
      "rightVisualText": "Instant Load"
    },
    {
      "title": "3. COMPONENT ARCHITECTURE",
      "leftTitle": "JSX, compilation",
      "rightTitle": "JSX, serialization",
      "leftDesc": "SolidJS compiles JSX to efficient vanilla JS and DOM operations.",
      "rightDesc": "Qwik serializes component state and logic for efficient resuming.",
      "leftIcon": "Code",
      "rightIcon": "FileCode",
      "leftVisualText": "Compiled JSX",
      "rightVisualText": "Serialized State"
    },
    {
      "title": "4. STATE MANAGEMENT",
      "leftTitle": "Signals & Stores",
      "rightTitle": "Context & Stores",
      "leftDesc": "Primarily uses signals, providing granular control and performance.",
      "rightDesc": "Leverages context and stores, designed to be resumable.",
      "leftIcon": "Layers",
      "rightIcon": "Layers",
      "leftVisualText": "Signals",
      "rightVisualText": "Resumable Stores"
    },
    {
      "title": "5. PERFORMANCE",
      "leftTitle": "Runtime efficiency",
      "rightTitle": "Load time optimization",
      "leftDesc": "Excellent runtime performance due to fine-grained reactivity.",
      "rightDesc": "Superior initial load times and interactivity.",
      "leftIcon": "Cpu",
      "rightIcon": "Network",
      "leftVisualText": "Runtime Speed",
      "rightVisualText": "Load Speed"
    },
    {
      "title": "6. ECOSYSTEM SIZE",
      "leftTitle": "Growing rapidly",
      "rightTitle": "Emerging ecosystem",
      "leftDesc": "SolidJS has a strong and active community with growing library support.",
      "rightDesc": "Qwik is newer, its ecosystem is still developing.",
      "leftIcon": "Globe",
      "rightIcon": "Globe",
      "leftVisualText": "Mature",
      "rightVisualText": "New"
    },
    {
      "title": "7. LEARNING CURVE",
      "leftTitle": "Familiar concepts",
      "rightTitle": "New paradigms",
      "leftDesc": "Easier transition for those familiar with reactive patterns.",
      "rightDesc": "Requires understanding resumability and its implications.",
      "leftIcon": "Unlock",
      "rightIcon": "Lock",
      "leftVisualText": "Easier",
      "rightVisualText": "Steeper"
    }
  ]
}